compartmental/__init__.py
compartmental/generic_model.py
compartmental/util.py
compartmental/parameters/__init__.py
compartmental/parameters/parameters_manager.py
compartmental-0.1.0.dist-info/LICENSE
compartmental-0.1.0.dist-info/METADATA
compartmental-0.1.0.dist-info/WHEEL
compartmental-0.1.0.dist-info/top_level.txt
compartmental-0.1.0.dist-info/RECORD
