Metadata-Version: 2.1
Name: compartmental
Version: 0.1.0
Summary: Compartmental models with ABC inference optimized for GPU use
Author-email: Unai Lería Fortea <unaileria@gmail.com>
Maintainer-email: Unai Lería Fortea <unaileria@gmail.com>
License: Apache License 2.0
Project-URL: GitHub, https://github.com/QuanticPony/compartmental
Project-URL: Documentation, https://QuanticPony/.github.io/compartmental/
Keywords: compartmental models,fit,analysis,ABC,computation
Classifier: Intended Audience :: Education
Classifier: Intended Audience :: Science/Research
Classifier: Programming Language :: Python :: 3
Classifier: License :: OSI Approved :: Apache Software License
Classifier: Operating System :: OS Independent
Classifier: Topic :: Education
Classifier: Topic :: Scientific/Engineering
Classifier: Topic :: Scientific/Engineering :: Visualization
Requires-Python: >=3.8
License-File: LICENSE
Requires-Dist: numpy
